code140.v

/******************************************************************************/
/* Sample Verilog HDL Code for Computer Logic Design     Arch Lab. TOKYO TECH */
/******************************************************************************/
`default_nettype none

/******************************************************************************/
`define NOP  {21'h0, 11'h20}
`define ADD  6'h0
`define ADDI 6'h8
`define LW   6'h23
`define SW   6'h2b
`define BEQ  6'h4
`define BNE  6'h5
`define HALT 6'h11 /* this is not for MIPS */
/******************************************************************************/

module m_top ();
  reg r_clk=0; initial forever #100 r_clk = ~r_clk;
  reg r_rst=0;

  wire w_halt;
  wire [31:0] w_rout;
  m_proc11 p (r_clk, r_rst, w_rout, w_halt);
  always@(posedge r_clk) if (w_halt) $finish;
  always@(posedge r_clk) if (r_cnt>=100) $finish;//デバック用
  reg [31:0] r_cnt = 0;
  always@(posedge r_clk) r_cnt <= r_cnt + 1;
  always@(posedge r_clk) begin #90
    $write("%8d : %x %x[%x] %x %x %x | MeWb_rd2 %d %d | ExMe_rd2 %d [w_rrs %d w_rrt %d w_rrt2 %d]|ExMe_rslt %d MeWb_rslt %d\n",
       r_cnt, p.r_pc, p.IfId_pc, p.w_op, p.IdEx_pc, p.ExMe_pc, p.MeWb_pc,
       p.MeWb_rd2, p.w_rslt2, p.ExMe_rd2, p.w_rrs,p.w_rrt, p.w_rrt2,p.ExMe_rslt, p.MeWb_rslt);
  end

  initial begin
    $dumpfile("code140_id.vcd");
    $dumpvars(0, p);
  end
endmodule

/******************************************************************************/
/*
module m_main (w_clk, w_btnu, w_btnd, w_led, r_sg, r_an);
  input  wire w_clk, w_btnu, w_btnd;
  output wire [15:0] w_led;
  output reg [6:0] r_sg;  // cathode segments
  output reg [7:0] r_an;  // common anode
  wire w_clk2=w_clk, w_locked=1;
  //clk_wiz_0 clk_wiz (w_clk2, 0, w_locked, w_clk);
  wire w_rst = ~w_locked;
  wire [31:0] w_rout;
  wire w_halt;
  m_proc11 p (w_clk2, w_rst, w_rout, w_halt);
  reg [31:0] r_cnt = 0;
  always @(posedge w_clk2) r_cnt <= (w_rst) ? 0 : (~w_halt) ? r_cnt + 1 : r_cnt;
  wire [31:0] w_data = (w_btnu) ? r_cnt : w_rout;
  assign w_led = (w_btnd) ? w_data[31:16] : w_data[15:0];
  wire [6:0] w_sg;
  wire [7:0] w_an;
  m_7segcon m_7segcon(w_clk2, w_data, w_sg, w_an);
  always @(posedge w_clk2) r_sg <= w_sg;
  always @(posedge w_clk2) r_an <= w_an;
endmodule
*/
/******************************************************************************/
module m_proc11 (w_clk, w_rst, r_rout, r_halt);
  input  wire w_clk, w_rst;
  output reg [31:0] r_rout;
  output reg        r_halt;

  reg  [31:0] IfId_pc4=0, Idhalf_pc4=0;                      // pipe regs
  reg  [31:0] Idhalf_imm32=0, Idhalf_sftl2=0;                // plus
  reg  [31:0] IdEx_rrs=0, IdEx_rrt=0, IdEx_rrt2=0;           //
  reg   [5:0] Idhalf_rs=0,IdEx_rs=0, Idhalf_rt=0, IdEx_rt=0; //plus alpha for mux
  reg  [31:0] ExMe_rslt=0, ExMe_rrt=0, Wb_rslt2=0;                       //
  reg  [31:0] MeWb_rslt=0;                                   //
  reg   [5:0]             Idhalf_op=0, IdEx_op=0,  ExMe_op=0,  MeWb_op=0; //
  reg  [31:0] Idhalf_pc=0, IfId_pc=0,  IdEx_pc=0,  ExMe_pc=0,  MeWb_pc=0; //
  reg   [4:0] Idhalf_rd2=0, IfId_rd2=0, IdEx_rd2=0, ExMe_rd2=0, MeWb_rd2=0, Wb_rd2=0;//
  reg         Idhalf_w=0, IfId_w=0,   IdEx_w=0,   ExMe_w=0,   MeWb_w=0, Wb_w=0;  //
  reg         Idhalf_we=0, IfId_we=0,  IdEx_we=0,  ExMe_we=0;             //
  reg IdEx_taken=0;
  wire [31:0] IfId_ir, IfId_ir2, MeWb_ldd;                             // note
  /**************************** IF stage **********************************/
  wire w_taken;
  wire [31:0] w_tpc;
  reg  [31:0] r_pc  = 0;
  wire [31:0] w_pc4 = r_pc + 4;
  m_memory m_imem (w_clk, r_pc[13:2], 1'b0, 0, IfId_ir);
  always @(posedge w_clk) begin
    r_pc     <= #3 (w_rst | r_halt) ? 0 : (w_taken) ? w_tpc : w_pc4;
    IfId_pc  <= #3 r_pc;
    IfId_pc4 <= #3 w_pc4;
  end
  /**************************** ID1 stage ***********************************/
  wire [31:0] w_rrs = 0, w_rrt = 0;
  wire [31:0] w_rslt2;
  wire  [5:0] w_op    = IfId_ir2[31:26];
  wire  [4:0] w_rs    = IfId_ir2[25:21];
  wire  [4:0] w_rt    = IfId_ir2[20:16];
  wire  [4:0] w_rd    = IfId_ir2[15:11];
  wire  [4:0] w_rd2   = (w_op!=0) ? w_rt : w_rd;
  wire [15:0] w_imm   = IfId_ir2[15:0];
  wire [31:0] w_imm32 = {{16{w_imm[15]}}, w_imm};
  assign IfId_ir2 = (IdEx_taken) ? `NOP : IfId_ir;
  m_regfile m_regs (w_clk, w_rs, w_rt, MeWb_rd2, MeWb_w, w_rslt2, w_rrs, w_rrt);
  reg [31:0] r_check1=0, r_check2=0;
  always @(posedge w_clk) begin
    r_check1 <= #15 w_rrs;
    r_check2 <= #15 w_rrt;
    Idhalf_sftl2 <= #3 {w_imm32[29:0], 2'h0};
    Idhalf_imm32 <= #3 {{16{w_imm[15]}}, w_imm};
    Idhalf_pc   <= #3 IfId_pc;
    Idhalf_pc4  <= #3 IfId_pc4;
    Idhalf_op   <= #3 w_op;
    Idhalf_rd2  <= #3 w_rd2;
    Idhalf_w    <= #3 (w_op==0 || (w_op>6'h5 && w_op<6'h28));
    Idhalf_we   <= #3 (w_op>6'h27);
    Idhalf_rs   <= #3 w_rs;//tasita
    Idhalf_rt   <= #3 (w_op==0) ? w_rt : 0;//tasita zisinnnai
  end


  /**************************** ID2 stage ***********************************/
  wire [31:0] w_rrt2  = (Idhalf_op>6'h5) ? Idhalf_imm32 : w_rrt;
  assign      w_tpc   = Idhalf_pc4 + Idhalf_sftl2;
  assign      w_taken = (Idhalf_op==`BNE && w_rrs!=w_rrt) ||(Idhalf_op==`BEQ && w_rrs==w_rrt);


  always @(posedge w_clk) begin
    IdEx_taken<= #3 w_taken;
    IdEx_pc   <= #3 Idhalf_pc;
    IdEx_op   <= #3 Idhalf_op;
    IdEx_rd2  <= #3 Idhalf_rd2;
    IdEx_w    <= #3 Idhalf_w;
    IdEx_we   <= #3 Idhalf_we;
    IdEx_rrs  <= #3 w_rrs;
    IdEx_rrt  <= #3 w_rrt;
    IdEx_rrt2 <= #3 w_rrt2;
    IdEx_rs   <= #3 Idhalf_rs;
    IdEx_rt   <= #3 Idhalf_rt;
  end
  /**************************** EX stage ***********************************/
  //mux for data hazard
  wire [31:0] w_plus1, w_plus2_1,w_plus2_2;
  wire [31:0] w_rrt_for;
  assign w_plus1 = ((IdEx_rs == ExMe_rd2) && (ExMe_rd2 != 0) && ExMe_w) ? ExMe_rslt :
  ((MeWb_rd2 != 0)&& (MeWb_rd2 == IdEx_rs)&& MeWb_w)? w_rslt2  :
  ((Wb_rd2 != 0)&& (Wb_rd2 == IdEx_rs)&& Wb_w) ? Wb_rslt2 : IdEx_rrs;//mux

  assign w_plus2_1 = ((IdEx_rt == ExMe_rd2) && (ExMe_rd2 != 0) && ExMe_w) ? ExMe_rslt :
  ((MeWb_rd2 != 0) && (IdEx_rt == MeWb_rd2)&& MeWb_w) ? w_rslt2 :
  ((Wb_rd2 != 0)&& (Wb_rd2 == IdEx_rt)&& Wb_w) ? Wb_rslt2 : IdEx_rrt2;//mux

  assign w_rrt_for = ((IdEx_rt == ExMe_rd2) && (ExMe_rd2 != 0) && ExMe_w) ? ExMe_rslt :
  ((MeWb_rd2 != 0) && (IdEx_rt == MeWb_rd2)&& MeWb_w) ? w_rslt2 :
  ((Wb_rd2 != 0)&& (Wb_rd2 == IdEx_rt)&& Wb_w) ? Wb_rslt2 : IdEx_rrt;//mux

  assign w_plus2_2 = (ExMe_op > 6'h5) ? IdEx_rrt2 : w_plus2_1;

  wire [31:0] #10 w_rslt = w_plus1 + w_plus2_2; // ALU origin

  always @(posedge w_clk) begin
    ExMe_pc   <= #3 IdEx_pc;
    ExMe_op   <= #3 IdEx_op;
    ExMe_rd2  <= #3 IdEx_rd2;
    ExMe_w    <= #3 IdEx_w;
    ExMe_we   <= #3 IdEx_we;
    ExMe_rslt <= #3 w_rslt;
    ExMe_rrt  <= #3 w_rrt_for;
  end
  /**************************** MEM stage **********************************/
  m_memory m_dmem (w_clk, ExMe_rslt[13:2], ExMe_we, ExMe_rrt, MeWb_ldd);
  always @(posedge w_clk) begin
    MeWb_pc   <= #3 ExMe_pc;
    MeWb_rslt <= #3 ExMe_rslt;
    MeWb_op   <= #3 ExMe_op;
    MeWb_rd2  <= #3 ExMe_rd2;
    MeWb_w    <= #3 ExMe_w;
  end
  /**************************** WB stage ***********************************/
  assign w_rslt2 = (MeWb_op>6'h19 && MeWb_op<6'h28) ? MeWb_ldd : MeWb_rslt;
  /*************************************************************************/
  initial r_halt = 0;
  always @(posedge w_clk) if (MeWb_op==`HALT) r_halt <= 1;
  initial r_rout = 0;
  reg [31:0] r_tmp=0;
  always @(posedge w_clk) begin//for original deta hazard
    Wb_rd2 <= #3 MeWb_rd2;
    Wb_w   <= #3 MeWb_w;
    Wb_rslt2 <= #3 w_rslt2;
  end
  always @(posedge w_clk) r_tmp <= (w_rst) ? 0 : (w_rs==30) ? w_rrs : r_tmp;
  always @(posedge w_clk) r_rout <= r_tmp;
endmodule

/******************************************************************************/
module m_memory (w_clk, w_addr, w_we, w_din, r_dout);
  input  wire w_clk, w_we;
  input  wire [11:0] w_addr;
  input  wire [31:0] w_din;
  output reg  [31:0] r_dout;
  reg [31:0] cm_ram [0:4095]; // 4K word (4096 x 32bit) memory
  always @(posedge w_clk) begin
    r_dout <= cm_ram[w_addr];
    if (w_we) cm_ram[w_addr] <= w_din;
  end
  initial r_dout = 0;


    initial begin
    cm_ram[0] ={`NOP};                            //     nop
    cm_ram[1] ={`NOP};                            //     nop
    cm_ram[2] ={`ADDI, 5'd0, 5'd20,16'd0};        //     addi $20, $0, 0
    cm_ram[3] ={`ADDI, 5'd0, 5'd21,16'd11};       //     addi $21, $0, 11
    cm_ram[4] ={`ADD,  5'd0, 5'd0, 5'd12,11'h20}; //     addi $12,$0, $0   // sum = 0;

    cm_ram[5] ={`ADDI, 5'd0, 5'd11,16'h0};        // L03 addi $11,$0, 0
    cm_ram[6] ={`ADDI, 5'd0, 5'd8, 16'd4096};     //     addi $8, $0, 4096
    cm_ram[7] ={`ADDI, 5'd0, 5'd9, 16'h0};        //     addi $9, $0, 0
    cm_ram[8] ={`ADDI, 5'd0, 5'd10,16'h0};        //     addi $10,$0, 0

    cm_ram[9] ={`SW,   5'd10,5'd11,16'd0};        // L01:sw   $11,0($10)
    cm_ram[10]={`ADDI, 5'd9, 5'd9, 16'h1};        //     addi $9, $9, 1
    cm_ram[11]={`ADDI, 5'd11,5'd11,16'h1};        //     addi $11,$11,1
    cm_ram[12]={`ADDI, 5'd11,5'd11,16'h1};        //     addi $11,$11,1
    cm_ram[13]={`ADDI, 5'd11,5'd11,16'h1};        //     addi $11,$11,1
    cm_ram[14]={`ADDI, 5'd11,5'd11,16'h1};        //     addi $11,$11,1
    cm_ram[15]={`ADDI, 5'd10,5'd10,16'h4};        //     addi $10,$10,4
    cm_ram[16]={`BNE,  5'd8, 5'd9, 16'hfff8};     //     bne  $8, $9, L01
    cm_ram[17]={`NOP};                            //     nop

    cm_ram[18]={`ADDI, 5'd0, 5'd8, 16'd4096};     //     addi $8, $0, 4096
    cm_ram[19]={`ADDI, 5'd0, 5'd9, 16'h0};        //     addi $9, $0, 0
    cm_ram[20]={`ADDI, 5'd0, 5'd10,16'h0};        //     addi $10,$0, 0

    cm_ram[21]={`LW,   5'd10,5'd11,16'd0};        // L02:lw   $11,0($10)
    cm_ram[22]={`ADDI, 5'd9, 5'd9, 16'h1};        //     addi $9, $9, 1
    cm_ram[23]={`ADDI, 5'd10,5'd10,16'h4};        //     addi $10,$10,4
    cm_ram[24]={`ADD,  5'd12,5'd11,5'd12,11'h20}; //     add  $12,$12,$11  // sum += $11
    cm_ram[25]={`ADDI, 5'd12,5'd12,16'h1};        //     addi $12,$12,1    // sum ++;
    cm_ram[26]={`ADDI, 5'd12,5'd12,16'hffff};     //     addi $12,$12,-1   // sum --;
    cm_ram[27]={`ADDI, 5'd12,5'd12,16'h1};        //     addi $12,$12,1    // sum ++;
    cm_ram[28]={`ADDI, 5'd12,5'd12,16'h1};        //     addi $12,$12,1    // sum ++;
    cm_ram[29]={`ADDI, 5'd12,5'd12,16'hffff};     //     addi $12,$12,-1   // sum --;
    cm_ram[30]={`ADDI, 5'd12,5'd12,16'h1};        //     addi $12,$12,1    // sum ++;
    cm_ram[31]={`ADDI, 5'd12,5'd12,16'hfffe};     //     addi $12,$12,-2   // sum -= 2;
    cm_ram[32]={`BNE,  5'd8, 5'd9, 16'hfff4};     //     bne  $8, $9, L02
    cm_ram[33]={`NOP};                            //     nop

    cm_ram[34]={`ADDI, 5'd20,5'd20,16'h1};        //     addi $20,$20,1    // j++
    cm_ram[35]={`ADDI, 5'd8, 5'd8,16'h11};        //     addi $8, $8, 0x11 //
    cm_ram[36]={`ADDI, 5'd8, 5'd8,16'h12};        //     addi $8, $8, 0x12 //
    cm_ram[37]={`ADDI, 5'd8, 5'd8,16'h13};        //     addi $8, $8, 0x13 //
    cm_ram[38]={`ADDI, 5'd8, 5'd8,16'h14};        //     addi $8, $8, 0x14 //
    cm_ram[39]={`BNE,  5'd20,5'd21,16'hffdd};     //     bne  $20,$21,L03  // (j<4) ?
    cm_ram[40]={`NOP};                            //     nop
    cm_ram[41]={`ADD,  5'd12,5'd0, 5'd30,11'h20}; //     add  $30,$12,$0
    cm_ram[42]={`ADD,  5'd30,5'd0, 5'd0, 11'h20}; //     add  $0, $30,$0 // 5ffa000
    cm_ram[43]={`HALT, 26'h0};                    //     halt
    cm_ram[44]={`NOP};                            //     nop
    cm_ram[45]={`NOP};                            //     nop
    cm_ram[46]={`NOP};                            //     nop
    cm_ram[47]={`NOP};                            //     nop
    cm_ram[48]={`NOP};                            //     nop
  end

  // initial begin
  //   cm_ram[0] ={`NOP};                            //     nop
  //   cm_ram[1] ={`ADDI, 5'd0, 5'd1, 16'h20};       //     addi $1,  $0, 0x20
  //   cm_ram[2] ={`SW,   5'd0, 5'd1, 16'd0};        //     sw   $1, 0($0)
  //   cm_ram[3] ={`ADDI, 5'd0, 5'd11,16'd2};        //     addi $11, $0, 2
  //   cm_ram[4] ={`ADDI, 5'd0, 5'd12,16'd3};        //     addi $12, $0, 3
  //   cm_ram[5] ={`ADDI, 5'd0, 5'd13,16'd4};        //     addi $13, $0, 4
  // //cm_ram[6] ={`ADDI, 5'd10,5'd10,16'h10};       //     addi $10, $10,0x10
  //   cm_ram[6] ={`ADDI, 5'd0,5'd10,16'h10};        //     addi $10, $0,0x10

  //   cm_ram[7] ={`ADDI, 5'd11,5'd11,16'h10};       //     addi $11, $11,0x10
  //   cm_ram[8] ={`ADDI, 5'd12,5'd12,16'h10};       //     addi $12, $12,0x10
  //   cm_ram[9] ={`ADDI, 5'd13,5'd13,16'h10};       //     addi $13, $13,0x10
  //   cm_ram[10]={`ADD,  5'd10,5'd1, 5'd10,11'h20}; //     add  $10,$10,$1
  //   cm_ram[11]={`ADD,  5'd11,5'd1, 5'd11,11'h20}; //     add  $11,$11,$1
  //   cm_ram[12]={`ADD,  5'd12,5'd1, 5'd12,11'h20}; //     add  $12,$12,$1
  //   cm_ram[13]={`ADD,  5'd13,5'd1, 5'd13,11'h20}; //     add  $13,$13,$1
  //   cm_ram[14]={`HALT, 26'h0};                    //     halt
  //   cm_ram[15]={`NOP};                            //     nop
  //   cm_ram[16]={`NOP};                            //     nop
  //   cm_ram[17]={`NOP};                            //     nop
  //   cm_ram[18]={`NOP};                            //     nop
  //   cm_ram[19]={`NOP};                            //     nop
  // end

//    cm_ram[2] ={`SW,   5'd0, 5'd1, 16'd0};        //     sw   $1, 0($0)
//    cm_ram[2] ={`ADDI, 5'd0, 5'd10,16'd1};        //     addi $10, $0, 1
//    cm_ram[13] ={`LW,   5'd0, 5'd12, 16'd0};       //     lw   $12, 0($0)
//    cm_ram[8] ={`ADD,  5'd10,5'd11,5'd12,11'h20}; //     add  $12,$10,$11
//    cm_ram[8] ={`ADDI, 5'd12,5'd12,16'h10};       //     addi $12, $12,0x10
//    cm_ram[13]={`ADD,  5'd13,5'd1, 5'd13,11'h20}; //     add  $13,$13,$1
endmodule

/******************************************************************************/
module m_regfile (w_clk, w_rr1, w_rr2, w_wr, w_we, w_wdata, r_rdata1, r_rdata2);
  input  wire        w_clk;
  input  wire  [4:0] w_rr1, w_rr2, w_wr;
  input  wire [31:0] w_wdata;
  input  wire        w_we;
  output reg [31:0] r_rdata1, r_rdata2;//initial
  //reg [4:0] r_rr1=0, r_rr2=0;

  reg [31:0] r[0:31];
  always @(posedge w_clk) begin
    r_rdata1 <= #15 (w_rr1==0) ? 0 : (w_we && (w_rr1==w_wr)) ? w_wdata : r[w_rr1];
    r_rdata2 <= #15 (w_rr2==0) ? 0 : (w_we && (w_rr2==w_wr)) ? w_wdata : r[w_rr2];
    if(w_we) r[w_wr] <= w_wdata;
  end

  initial begin
    r[1] = 1;
    r[2] = 2;
    r_rdata1=0;
    r_rdata2=0;
  end
endmodule

/******************************************************************************/
module m_7segled (w_in, r_led);
  input  wire [3:0] w_in;
  output reg  [6:0] r_led;
  always @(*) begin
    case (w_in)
      4'h0  : r_led <= 7'b1111110;
      4'h1  : r_led <= 7'b0110000;
      4'h2  : r_led <= 7'b1101101;
      4'h3  : r_led <= 7'b1111001;
      4'h4  : r_led <= 7'b0110011;
      4'h5  : r_led <= 7'b1011011;
      4'h6  : r_led <= 7'b1011111;
      4'h7  : r_led <= 7'b1110000;
      4'h8  : r_led <= 7'b1111111;
      4'h9  : r_led <= 7'b1111011;
      4'ha  : r_led <= 7'b1110111;
      4'hb  : r_led <= 7'b0011111;
      4'hc  : r_led <= 7'b1001110;
      4'hd  : r_led <= 7'b0111101;
      4'he  : r_led <= 7'b1001111;
      4'hf  : r_led <= 7'b1000111;
      default:r_led <= 7'b0000000;
    endcase
  end
endmodule

`define DELAY7SEG  100000 // 200000 for 100MHz, 100000 for 50MHz
/******************************************************************************/
module m_7segcon (w_clk, w_din, r_sg, r_an);
  input  wire w_clk;
  input  wire [31:0] w_din;
  output reg [6:0] r_sg;  // cathode segments
  output reg [7:0] r_an;  // common anode

  reg [31:0] r_val   = 0;
  reg [31:0] r_cnt   = 0;
  reg  [3:0] r_in    = 0;
  reg  [2:0] r_digit = 0;
  always@(posedge w_clk) r_val <= w_din;

  always@(posedge w_clk) begin
    r_cnt <= (r_cnt>=(`DELAY7SEG-1)) ? 0 : r_cnt + 1;
    if(r_cnt==0) begin
      r_digit <= r_digit+ 1;
      if      (r_digit==0) begin r_an <= 8'b11111110; r_in <= r_val[3:0];   end
      else if (r_digit==1) begin r_an <= 8'b11111101; r_in <= r_val[7:4];   end
      else if (r_digit==2) begin r_an <= 8'b11111011; r_in <= r_val[11:8];  end
      else if (r_digit==3) begin r_an <= 8'b11110111; r_in <= r_val[15:12]; end
      else if (r_digit==4) begin r_an <= 8'b11101111; r_in <= r_val[19:16]; end
      else if (r_digit==5) begin r_an <= 8'b11011111; r_in <= r_val[23:20]; end
      else if (r_digit==6) begin r_an <= 8'b10111111; r_in <= r_val[27:24]; end
      else                 begin r_an <= 8'b01111111; r_in <= r_val[31:28]; end
    end
  end
  wire [6:0] w_segments;
  m_7segled m_7segled (r_in, w_segments);
  always@(posedge w_clk) r_sg <= ~w_segments;
endmodule
/******************************************************************************/

code140_id.vcd
$date
	Tue Jun  4 21:21:01 2019
$end
$version
	Icarus Verilog
$end
$timescale
	1s
$end
$scope module m_top $end
$scope module p $end
$var wire 1 ! w_clk $end
$var wire 32 " w_rrs [31:0] $end
$var wire 32 # w_rrt [31:0] $end
$var wire 1 $ w_rst $end
$var wire 1 % w_taken $end
$var wire 32 & w_tpc [31:0] $end
$var wire 5 ' w_rt [4:0] $end
$var wire 32 ( w_rslt2 [31:0] $end
$var wire 32 ) w_rslt [31:0] $end
$var wire 5 * w_rs [4:0] $end
$var wire 32 + w_rrt_for [31:0] $end
$var wire 32 , w_rrt2 [31:0] $end
$var wire 5 - w_rd2 [4:0] $end
$var wire 5 . w_rd [4:0] $end
$var wire 32 / w_plus2_2 [31:0] $end
$var wire 32 0 w_plus2_1 [31:0] $end
$var wire 32 1 w_plus1 [31:0] $end
$var wire 32 2 w_pc4 [31:0] $end
$var wire 6 3 w_op [5:0] $end
$var wire 32 4 w_imm32 [31:0] $end
$var wire 16 5 w_imm [15:0] $end
$var wire 32 6 MeWb_ldd [31:0] $end
$var wire 32 7 IfId_ir2 [31:0] $end
$var wire 32 8 IfId_ir [31:0] $end
$var reg 6 9 ExMe_op [5:0] $end
$var reg 32 : ExMe_pc [31:0] $end
$var reg 5 ; ExMe_rd2 [4:0] $end
$var reg 32 < ExMe_rrt [31:0] $end
$var reg 32 = ExMe_rslt [31:0] $end
$var reg 1 > ExMe_w $end
$var reg 1 ? ExMe_we $end
$var reg 6 @ IdEx_op [5:0] $end
$var reg 32 A IdEx_pc [31:0] $end
$var reg 5 B IdEx_rd2 [4:0] $end
$var reg 32 C IdEx_rrs [31:0] $end
$var reg 32 D IdEx_rrt [31:0] $end
$var reg 32 E IdEx_rrt2 [31:0] $end
$var reg 6 F IdEx_rs [5:0] $end
$var reg 6 G IdEx_rt [5:0] $end
$var reg 1 H IdEx_taken $end
$var reg 1 I IdEx_w $end
$var reg 1 J IdEx_we $end
$var reg 32 K Idhalf_imm32 [31:0] $end
$var reg 6 L Idhalf_op [5:0] $end
$var reg 32 M Idhalf_pc [31:0] $end
$var reg 32 N Idhalf_pc4 [31:0] $end
$var reg 5 O Idhalf_rd2 [4:0] $end
$var reg 6 P Idhalf_rs [5:0] $end
$var reg 6 Q Idhalf_rt [5:0] $end
$var reg 32 R Idhalf_sftl2 [31:0] $end
$var reg 1 S Idhalf_w $end
$var reg 1 T Idhalf_we $end
$var reg 32 U IfId_pc [31:0] $end
$var reg 32 V IfId_pc4 [31:0] $end
$var reg 5 W IfId_rd2 [4:0] $end
$var reg 1 X IfId_w $end
$var reg 1 Y IfId_we $end
$var reg 6 Z MeWb_op [5:0] $end
$var reg 32 [ MeWb_pc [31:0] $end
$var reg 5 \ MeWb_rd2 [4:0] $end
$var reg 32 ] MeWb_rslt [31:0] $end
$var reg 1 ^ MeWb_w $end
$var reg 5 _ Wb_rd2 [4:0] $end
$var reg 32 ` Wb_rslt2 [31:0] $end
$var reg 1 a Wb_w $end
$var reg 32 b r_check1 [31:0] $end
$var reg 32 c r_check2 [31:0] $end
$var reg 1 d r_halt $end
$var reg 32 e r_pc [31:0] $end
$var reg 32 f r_rout [31:0] $end
$var reg 32 g r_tmp [31:0] $end
$scope module m_dmem $end
$var wire 12 h w_addr [11:0] $end
$var wire 1 ! w_clk $end
$var wire 32 i w_din [31:0] $end
$var wire 1 ? w_we $end
$var reg 32 j r_dout [31:0] $end
$upscope $end
$scope module m_imem $end
$var wire 12 k w_addr [11:0] $end
$var wire 1 ! w_clk $end
$var wire 32 l w_din [31:0] $end
$var wire 1 m w_we $end
$var reg 32 n r_dout [31:0] $end
$upscope $end
$scope module m_regs $end
$var wire 1 ! w_clk $end
$var wire 5 o w_rr1 [4:0] $end
$var wire 5 p w_rr2 [4:0] $end
$var wire 32 q w_wdata [31:0] $end
$var wire 1 ^ w_we $end
$var wire 5 r w_wr [4:0] $end
$var reg 32 s r_rdata1 [31:0] $end
$var reg 32 t r_rdata2 [31:0] $end
$upscope $end
$upscope $end
$upscope $end
$enddefinitions $end
#0
$dumpvars
b0 t
b0 s
b0 r
b0 q
b0 p
b0 o
b0 n
0m
b0 l
b0 k
b0 j
b0 i
b0 h
b0 g
b0 f
b0 e
0d
b0 c
b0 b
0a
b0 `
b0 _
0^
b0 ]
b0 \
b0 [
b0 Z
0Y
0X
b0 W
b0 V
b0 U
0T
0S
b0 R
b0 Q
b0 P
b0 O
b0 N
b0 M
b0 L
b0 K
0J
0I
0H
b0 G
b0 F
b0 E
b0 D
b0 C
b0 B
b0 A
b0 @
0?
0>
b0 =
b0 <
b0 ;
b0 :
b0 9
b0 8
b0 7
b0 6
b0 5
b0 4
b0 3
b100 2
b0 1
b0 0
b0 /
b0 .
b0 -
b0 ,
b0 +
b0 *
bx )
b0 (
b0 '
b0 &
0%
0$
b0 #
b0 "
0!
$end
#10
b0 )
#100
b100000 4
b100000 5
b100000 7
b100000 8
b100000 n
b100000 6
b100000 j
1!
#103
b1 k
b100 V
b1000 2
b100 e
1S
#200
0!
#300
1!
#303
b10 k
1I
b100 N
b100000 K
b10000100 &
b10000000 R
b1000 V
b100 U
b1100 2
b1000 e
#400
0!
#500
b10100 -
b0 4
b0 5
b10100 '
b10100 p
b1000 3
b100000000101000000000000000000 7
b100000000101000000000000000000 8
b100000000101000000000000000000 n
1!
#503
b11 k
b1100 V
b1000 U
b10000 2
b1100 e
b10001000 &
b1000 N
b100 M
1>
#600
0!
#700
b10101 -
b1011 4
b1011 5
b10101 '
b10101 p
b100000000101010000000000001011 7
b100000000101010000000000001011 8
b100000000101010000000000001011 n
1!
#703
b100 k
1^
b100 A
b10100 O
b1000 L
b1100 N
b1000 M
b0 K
b1100 &
b0 R
b10000 V
b1100 U
b10100 2
b10000 e
#715
bx #
bx t
#800
0!
#900
b1100 -
b110000000100000 4
b110000000100000 5
b1100 .
b0 '
b0 p
b0 3
b110000000100000 7
b110000000100000 8
b110000000100000 n
1!
#903
bx +
b101 k
b1011 ,
b10100 V
b10000 U
b11000 2
b10100 e
b10101 O
b10000 N
b1100 M
b1011 K
b111100 &
b101100 R
bx D
b10100 B
b1000 @
b1000 A
b100 :
1a
#915
bx c
#1000
0!
#1100
b1011 -
b0 4
b0 5
b0 .
b1011 '
b1011 p
b1000 3
b100000000010110000000000000000 7
b100000000010110000000000000000 8
b100000000010110000000000000000 n
1!
#1103
b1011 0
b1011 /
bx ,
b110 k
b100 [
bx <
bx i
b10100 ;
b1000 9
b1000 :
b1011 E
b10101 B
b1100 A
b1100 O
b0 L
b10100 N
b10000 M
b110000000100000 K
b11000000010010100 &
b11000000010000000 R
b11000 V
b10100 U
b11100 2
b11000 e
#1113
b1011 )
#1115
b0 ,
b0 #
b0 t
#1200
0!
#1300
b1000 -
b1000000000000 4
b1000000000000 5
b10 .
b1000 '
b1000 p
b100000000010000001000000000000 7
b100000000010000001000000000000 8
b100000000010000001000000000000 n
1!
#1303
b0 0
b0 +
b111 k
b0 /
b10 h
b11100 V
b11000 U
b100000 2
b11100 e
b1011 O
b1000 L
b11000 N
b10100 M
b0 K
b11000 &
b0 R
b0 E
b0 D
b1100 B
b0 @
b10000 A
b1011 =
b10101 ;
b1100 :
b10100 \
b10100 r
b1000 Z
b1000 [
#1313
b0 )
#1315
bx #
bx t
b0 c
#1400
0!
#1500
b1001 -
b0 4
b0 5
b0 .
b1001 '
b1001 p
b100000000010010000000000000000 7
b100000000101000000000000000000 6
b100000000101000000000000000000 j
b100000000010010000000000000000 8
b100000000010010000000000000000 n
1!
#1503
bx +
b1011 (
b1011 q
b0 h
b1000000000000 ,
b1000 k
b10100 _
b10101 \
b10101 r
b1011 ]
b1100 [
b0 <
b0 i
b0 =
b1100 ;
b0 9
b10000 :
bx D
b1011 B
b1000 @
b10100 A
b1000 O
b11100 N
b11000 M
b1000000000000 K
b100000000011100 &
b100000000000000 R
b100000 V
b11100 U
b100100 2
b100000 e
#1515
bx c
#1600
0!
#1700
b1010 -
b1010 '
b1010 p
b100000000010100000000000000000 7
b100000000010100000000000000000 8
b100000000010100000000000000000 n
b100000 6
b100000 j
1!
#1703
b1000000000000 0
b1001 k
b0 ,
b1000000000000 /
b0 (
b0 q
b100100 V
b100000 U
b101000 2
b100100 e
b1001 O
b100000 N
b11100 M
b0 K
b100000 &
b0 R
b1000000000000 E
b1000 B
b11000 A
bx <
bx i
b1011 ;
b1000 9
b10100 :
b1100 \
b1100 r
b0 Z
b0 ]
b10000 [
b1011 `
b10101 _
#1713
b1000000000000 )
#1800
0!
#1900
b1011 -
b1011 '
b1011 p
b1010 *
b1010 o
b101011 3
b10101101010010110000000000000000 7
b10101101010010110000000000000000 8
b10101101010010110000000000000000 n
1!
#1903
b0 0
b10000000000 h
b0 /
b1010 k
b0 `
b1100 _
b1011 \
b1011 r
b1000 Z
b10100 [
b1000000000000 =
b1000 ;
b11000 :
b0 E
b1001 B
b11100 A
b1010 O
b100100 &
b100100 N
b100000 M
b101000 V
b100100 U
b101100 2
b101000 e
#1913
b0 )
#2000
0!
#2100
b1001 -
b1 4
b1 5
b1001 '
b1001 p
b1001 *
b1001 o
b1000 3
b100001001010010000000000000001 7
b100001001010010000000000000001 8
b100001001010010000000000000001 n
bx 6
bx j
1!
#2103
b1011 k
b0 h
b1000000000000 (
b1000000000000 q
b101100 V
b101000 U
b110000 2
b101100 e
b1010 P
1T
0S
b1011 O
b101011 L
b101000 &
b101000 N
b100100 M
b1010 B
b100000 A
b0 =
b1001 ;
b11100 :
b1000 \
b1000 r
b1000000000000 ]
b11000 [
b1011 _
#2115
b0 #
b0 t
bx "
bx s
#2200
0!
#2300
b1011 -
b1011 '
b1011 p
b1011 *
b1011 o
b100001011010110000000000000001 7
b100000 6
b100000 j
b100001011010110000000000000001 8
b100001011010110000000000000001 n
1!
