code140.v

/******************************************************************************/
/* Sample Verilog HDL Code for Computer Logic Design     Arch Lab. TOKYO TECH */
/******************************************************************************/
`default_nettype none

/******************************************************************************/
`define NOP  {21'h0, 11'h20}
`define ADD  6'h0
`define ADDI 6'h8
`define LW   6'h23
`define SW   6'h2b
`define BEQ  6'h4
`define BNE  6'h5
`define HALT 6'h11 /* this is not for MIPS */
/******************************************************************************/

module m_top ();
  reg r_clk=0; initial forever #50 r_clk = ~r_clk;
  reg r_rst=0;

  wire w_halt;
  wire [31:0] w_rout;
  m_proc11 p (r_clk, r_rst, w_rout, w_halt);
  always@(posedge r_clk) if (w_halt) $finish;
  always@(posedge r_clk) if (r_cnt>=100) $finish;//デバック用
  reg [31:0] r_cnt = 0;
  always@(posedge r_clk) r_cnt <= r_cnt + 1;
  always@(posedge r_clk) begin #90
    $write("%8d : %x %x[%x] %x %x %x | MeWb_rd2 %d %d | ExMe_rd2 %d [w_rrs %d w_rrt %d w_rrt2 %d]|ExMe_rslt %d MeWb_rslt %d\n",
       r_cnt, p.r_pc, p.IfId_pc, p.w_op, p.IdEx_pc, p.ExMe_pc, p.MeWb_pc,
       p.MeWb_rd2, p.w_rslt2, p.ExMe_rd2, p.w_rrs,p.w_rrt, p.w_rrt2,p.ExMe_rslt, p.MeWb_rslt);
  end
  initial begin
    $dumpfile("code140.vcd");
    $dumpvars(0, p);
  end
endmodule

/******************************************************************************/
/*
module m_main (w_clk, w_btnu, w_btnd, w_led, r_sg, r_an);
  input  wire w_clk, w_btnu, w_btnd;
  output wire [15:0] w_led;
  output reg [6:0] r_sg;  // cathode segments
  output reg [7:0] r_an;  // common anode
  wire w_clk2=w_clk, w_locked=1;
  //clk_wiz_0 clk_wiz (w_clk2, 0, w_locked, w_clk);
  wire w_rst = ~w_locked;
  wire [31:0] w_rout;
  wire w_halt;
  m_proc11 p (w_clk2, w_rst, w_rout, w_halt);
  reg [31:0] r_cnt = 0;
  always @(posedge w_clk2) r_cnt <= (w_rst) ? 0 : (~w_halt) ? r_cnt + 1 : r_cnt;
  wire [31:0] w_data = (w_btnu) ? r_cnt : w_rout;
  assign w_led = (w_btnd) ? w_data[31:16] : w_data[15:0];
  wire [6:0] w_sg;
  wire [7:0] w_an;
  m_7segcon m_7segcon(w_clk2, w_data, w_sg, w_an);
  always @(posedge w_clk2) r_sg <= w_sg;
  always @(posedge w_clk2) r_an <= w_an;
endmodule
*/
/******************************************************************************/
module m_proc11 (w_clk, w_rst, r_rout, r_halt);
  input  wire w_clk, w_rst;
  output reg [31:0] r_rout;
  output reg        r_halt;

  reg  [31:0] IfId_pc4=0;                                    // pipe regs
  reg  [31:0] IdEx_rrs=0, IdEx_rrt=0, IdEx_rrt2=0;           //
  reg   [5:0] IdEx_rs=0, IdEx_rt=0;                          //plus alpha for mux
  reg  [31:0] ExMe_rslt=0, ExMe_rrt=0;                       //
  reg  [31:0] MeWb_rslt=0;                                   //
  reg   [5:0]             IdEx_op=0,  ExMe_op=0,  MeWb_op=0; //
  reg  [31:0] IfId_pc=0,  IdEx_pc=0,  ExMe_pc=0,  MeWb_pc=0; //
  reg   [4:0] IfId_rd2=0, IdEx_rd2=0, ExMe_rd2=0, MeWb_rd2=0;//
  reg         IfId_w=0,   IdEx_w=0,   ExMe_w=0,   MeWb_w=0;  //
  reg         IfId_we=0,  IdEx_we=0,  ExMe_we=0;             //
  wire [31:0] IfId_ir, MeWb_ldd;                             // note
  /**************************** IF stage **********************************/
  wire w_taken;
  wire [31:0] w_tpc;
  reg  [31:0] r_pc  = 0;
  wire [31:0] w_pc4 = r_pc + 4;
  m_memory m_imem (w_clk, r_pc[13:2], 1'b0, 0, IfId_ir);
  always @(posedge w_clk) begin
    r_pc     <= #3 (w_rst | r_halt) ? 0 : (w_taken) ? w_tpc : w_pc4;
    IfId_pc  <= #3 r_pc;
    IfId_pc4 <= #3 w_pc4;
  end
  /**************************** ID stage ***********************************/
  wire [31:0] w_rrs, w_rrt, w_rslt2;
  wire  [5:0] w_op    = IfId_ir[31:26];
  wire  [4:0] w_rs    = IfId_ir[25:21];
  wire  [4:0] w_rt    = IfId_ir[20:16];
  wire  [4:0] w_rd    = IfId_ir[15:11];
  wire  [4:0] w_rd2   = (w_op!=0) ? w_rt : w_rd;
  wire [15:0] w_imm   = IfId_ir[15:0];
  wire [31:0] w_imm32 = {{16{w_imm[15]}}, w_imm};
  wire [31:0] w_rrt2  = (w_op>6'h5) ? w_imm32 : w_rrt;
  assign      w_tpc   = IfId_pc4 + {w_imm32[29:0], 2'h0};
  assign      w_taken = (w_op==`BNE && w_rrs!=w_rrt) ||(w_op==`BEQ && w_rrs==w_rrt);
  m_regfile m_regs (w_clk, w_rs, w_rt, MeWb_rd2, MeWb_w, w_rslt2, w_rrs, w_rrt);

  always @(posedge w_clk) begin
    IdEx_pc   <= #3 IfId_pc;
    IdEx_op   <= #3 w_op;
    IdEx_rd2  <= #3 w_rd2;
    IdEx_w    <= #3 (w_op==0 || (w_op>6'h5 && w_op<6'h28));
    IdEx_we   <= #3 (w_op>6'h27);
    IdEx_rrs  <= #3 w_rrs;
    IdEx_rrt  <= #3 w_rrt;
    IdEx_rrt2 <= #3 w_rrt2;
    IdEx_rs   <= #3 w_rs;//tasita
    IdEx_rt   <= #3 (w_op==0) ? w_rt : 0;//tasita zisinnnai
  end
  /**************************** EX stage ***********************************/
  //mux for data hazard
  wire [31:0] w_plus1, w_plus2_1,w_plus2_2;
  assign w_plus1 = ((IdEx_rs == ExMe_rd2) && (ExMe_rd2 != 0) && ExMe_w) ? ExMe_rslt :
  ((MeWb_rd2 != 0)&& (MeWb_rd2 == IdEx_rs)&& MeWb_w)? w_rslt2 : IdEx_rrs;//mux

  assign w_plus2_1 = ((IdEx_rt == ExMe_rd2) && (ExMe_rd2 != 0) && ExMe_w) ? ExMe_rslt :
  ((MeWb_rd2 != 0) && (IdEx_rt == MeWb_rd2)&& MeWb_w) ? w_rslt2 : IdEx_rrt2;//mux

  assign w_plus2_2 = (ExMe_op > 6'h5) ? IdEx_rrt2 : w_plus2_1;

  wire [31:0] #10 w_rslt = w_plus1 + w_plus2_2; // ALU origin

  always @(posedge w_clk) begin
    ExMe_pc   <= #3 IdEx_pc;
    ExMe_op   <= #3 IdEx_op;
    ExMe_rd2  <= #3 IdEx_rd2;
    ExMe_w    <= #3 IdEx_w;
    ExMe_we   <= #3 IdEx_we;
    ExMe_rslt <= #3 w_rslt;
    ExMe_rrt  <= #3 IdEx_rrt;
  end
  /**************************** MEM stage **********************************/
  m_memory m_dmem (w_clk, ExMe_rslt[13:2], ExMe_we, ExMe_rrt, MeWb_ldd);
  always @(posedge w_clk) begin
    MeWb_pc   <= #3 ExMe_pc;
    MeWb_rslt <= #3 ExMe_rslt;
    MeWb_op   <= #3 ExMe_op;
    MeWb_rd2  <= #3 ExMe_rd2;
    MeWb_w    <= #3 ExMe_w;
  end
  /**************************** WB stage ***********************************/
  assign w_rslt2 = (MeWb_op>6'h19 && MeWb_op<6'h28) ? MeWb_ldd : MeWb_rslt;
  /*************************************************************************/
  initial r_halt = 0;
  always @(posedge w_clk) if (MeWb_op==`HALT) r_halt <= 1;
  initial r_rout = 0;
  reg [31:0] r_tmp=0;
  always @(posedge w_clk) r_tmp <= (w_rst) ? 0 : (w_rs==30) ? w_rrs : r_tmp;
  always @(posedge w_clk) r_rout <= r_tmp;
endmodule

/******************************************************************************/
module m_memory (w_clk, w_addr, w_we, w_din, r_dout);
  input  wire w_clk, w_we;
  input  wire [11:0] w_addr;
  input  wire [31:0] w_din;
  output reg  [31:0] r_dout;
  reg [31:0] cm_ram [0:4095]; // 4K word (4096 x 32bit) memory
  always @(posedge w_clk) begin
    r_dout <= cm_ram[w_addr];
    if (w_we) cm_ram[w_addr] <= w_din;
  end
  initial r_dout = 0;


    initial begin
    cm_ram[0] ={`NOP};                            //     nop
    cm_ram[1] ={`NOP};                            //     nop
    cm_ram[2] ={`ADDI, 5'd0, 5'd20,16'd0};        //     addi $20, $0, 0
    cm_ram[3] ={`ADDI, 5'd0, 5'd21,16'd11};       //     addi $21, $0, 11
    cm_ram[4] ={`ADD,  5'd0, 5'd0, 5'd12,11'h20}; //     addi $12,$0, $0   // sum = 0;

    cm_ram[5] ={`ADDI, 5'd0, 5'd11,16'h0};        // L03 addi $11,$0, 0
    cm_ram[6] ={`ADDI, 5'd0, 5'd8, 16'd4096};     //     addi $8, $0, 4096
    cm_ram[7] ={`ADDI, 5'd0, 5'd9, 16'h0};        //     addi $9, $0, 0
    cm_ram[8] ={`ADDI, 5'd0, 5'd10,16'h0};        //     addi $10,$0, 0

    cm_ram[9] ={`SW,   5'd10,5'd11,16'd0};        // L01:sw   $11,0($10)
    cm_ram[10]={`ADDI, 5'd9, 5'd9, 16'h1};        //     addi $9, $9, 1
    cm_ram[11]={`ADDI, 5'd11,5'd11,16'h1};        //     addi $11,$11,1
    cm_ram[12]={`ADDI, 5'd11,5'd11,16'h1};        //     addi $11,$11,1
    cm_ram[13]={`ADDI, 5'd11,5'd11,16'h1};        //     addi $11,$11,1
    cm_ram[14]={`ADDI, 5'd11,5'd11,16'h1};        //     addi $11,$11,1
    cm_ram[15]={`ADDI, 5'd10,5'd10,16'h4};        //     addi $10,$10,4
    cm_ram[16]={`BNE,  5'd8, 5'd9, 16'hfff8};     //     bne  $8, $9, L01
    cm_ram[17]={`NOP};                            //     nop

    cm_ram[18]={`ADDI, 5'd0, 5'd8, 16'd4096};     //     addi $8, $0, 4096
    cm_ram[19]={`ADDI, 5'd0, 5'd9, 16'h0};        //     addi $9, $0, 0
    cm_ram[20]={`ADDI, 5'd0, 5'd10,16'h0};        //     addi $10,$0, 0

    cm_ram[21]={`LW,   5'd10,5'd11,16'd0};        // L02:lw   $11,0($10)
    cm_ram[22]={`ADDI, 5'd9, 5'd9, 16'h1};        //     addi $9, $9, 1
    cm_ram[23]={`ADDI, 5'd10,5'd10,16'h4};        //     addi $10,$10,4
    cm_ram[24]={`ADD,  5'd12,5'd11,5'd12,11'h20}; //     add  $12,$12,$11  // sum += $11
    cm_ram[25]={`ADDI, 5'd12,5'd12,16'h1};        //     addi $12,$12,1    // sum ++;
    cm_ram[26]={`ADDI, 5'd12,5'd12,16'hffff};     //     addi $12,$12,-1   // sum --;
    cm_ram[27]={`ADDI, 5'd12,5'd12,16'h1};        //     addi $12,$12,1    // sum ++;
    cm_ram[28]={`ADDI, 5'd12,5'd12,16'h1};        //     addi $12,$12,1    // sum ++;
    cm_ram[29]={`ADDI, 5'd12,5'd12,16'hffff};     //     addi $12,$12,-1   // sum --;
    cm_ram[30]={`ADDI, 5'd12,5'd12,16'h1};        //     addi $12,$12,1    // sum ++;
    cm_ram[31]={`ADDI, 5'd12,5'd12,16'hfffe};     //     addi $12,$12,-2   // sum -= 2;
    cm_ram[32]={`BNE,  5'd8, 5'd9, 16'hfff4};     //     bne  $8, $9, L02
    cm_ram[33]={`NOP};                            //     nop

    cm_ram[34]={`ADDI, 5'd20,5'd20,16'h1};        //     addi $20,$20,1    // j++
    cm_ram[35]={`ADDI, 5'd8, 5'd8,16'h11};        //     addi $8, $8, 0x11 //
    cm_ram[36]={`ADDI, 5'd8, 5'd8,16'h12};        //     addi $8, $8, 0x12 //
    cm_ram[37]={`ADDI, 5'd8, 5'd8,16'h13};        //     addi $8, $8, 0x13 //
    cm_ram[38]={`ADDI, 5'd8, 5'd8,16'h14};        //     addi $8, $8, 0x14 //
    cm_ram[39]={`BNE,  5'd20,5'd21,16'hffdd};     //     bne  $20,$21,L03  // (j<4) ?
    cm_ram[40]={`NOP};                            //     nop
    cm_ram[41]={`ADD,  5'd12,5'd0, 5'd30,11'h20}; //     add  $30,$12,$0
    cm_ram[42]={`ADD,  5'd30,5'd0, 5'd0, 11'h20}; //     add  $0, $30,$0 // 5ffa000
    cm_ram[43]={`HALT, 26'h0};                    //     halt
    cm_ram[44]={`NOP};                            //     nop
    cm_ram[45]={`NOP};                            //     nop
    cm_ram[46]={`NOP};                            //     nop
    cm_ram[47]={`NOP};                            //     nop
    cm_ram[48]={`NOP};                            //     nop
  end

  // initial begin
  //   cm_ram[0] ={`NOP};                            //     nop
  //   cm_ram[1] ={`ADDI, 5'd0, 5'd1, 16'h20};       //     addi $1,  $0, 0x20
  //   cm_ram[2] ={`SW,   5'd0, 5'd1, 16'd0};        //     sw   $1, 0($0)
  //   cm_ram[3] ={`ADDI, 5'd0, 5'd11,16'd2};        //     addi $11, $0, 2
  //   cm_ram[4] ={`ADDI, 5'd0, 5'd12,16'd3};        //     addi $12, $0, 3
  //   cm_ram[5] ={`ADDI, 5'd0, 5'd13,16'd4};        //     addi $13, $0, 4
  // //cm_ram[6] ={`ADDI, 5'd10,5'd10,16'h10};       //     addi $10, $10,0x10
  //   cm_ram[6] ={`ADDI, 5'd0,5'd10,16'h10};        //     addi $10, $0,0x10

  //   cm_ram[7] ={`ADDI, 5'd11,5'd11,16'h10};       //     addi $11, $11,0x10
  //   cm_ram[8] ={`ADDI, 5'd12,5'd12,16'h10};       //     addi $12, $12,0x10
  //   cm_ram[9] ={`ADDI, 5'd13,5'd13,16'h10};       //     addi $13, $13,0x10
  //   cm_ram[10]={`ADD,  5'd10,5'd1, 5'd10,11'h20}; //     add  $10,$10,$1
  //   cm_ram[11]={`ADD,  5'd11,5'd1, 5'd11,11'h20}; //     add  $11,$11,$1
  //   cm_ram[12]={`ADD,  5'd12,5'd1, 5'd12,11'h20}; //     add  $12,$12,$1
  //   cm_ram[13]={`ADD,  5'd13,5'd1, 5'd13,11'h20}; //     add  $13,$13,$1
  //   cm_ram[14]={`HALT, 26'h0};                    //     halt
  //   cm_ram[15]={`NOP};                            //     nop
  //   cm_ram[16]={`NOP};                            //     nop
  //   cm_ram[17]={`NOP};                            //     nop
  //   cm_ram[18]={`NOP};                            //     nop
  //   cm_ram[19]={`NOP};                            //     nop
  // end

//    cm_ram[2] ={`SW,   5'd0, 5'd1, 16'd0};        //     sw   $1, 0($0)
//    cm_ram[2] ={`ADDI, 5'd0, 5'd10,16'd1};        //     addi $10, $0, 1
//    cm_ram[13] ={`LW,   5'd0, 5'd12, 16'd0};       //     lw   $12, 0($0)
//    cm_ram[8] ={`ADD,  5'd10,5'd11,5'd12,11'h20}; //     add  $12,$10,$11
//    cm_ram[8] ={`ADDI, 5'd12,5'd12,16'h10};       //     addi $12, $12,0x10
//    cm_ram[13]={`ADD,  5'd13,5'd1, 5'd13,11'h20}; //     add  $13,$13,$1
endmodule

/******************************************************************************/
module m_regfile (w_clk, w_rr1, w_rr2, w_wr, w_we, w_wdata, w_rdata1, w_rdata2);
  input  wire        w_clk;
  input  wire  [4:0] w_rr1, w_rr2, w_wr;
  input  wire [31:0] w_wdata;
  input  wire        w_we;
  output wire [31:0] w_rdata1, w_rdata2;

  reg [31:0] r[0:31];
  assign #15 w_rdata1 = (w_rr1==0) ? 0 :
   (w_we && (w_rr1==w_wr)) ? w_wdata :r[w_rr1];
  assign #15 w_rdata2 = (w_rr2==0) ? 0 :
   (w_we && (w_rr2==w_wr)) ? w_wdata : r[w_rr2];
  always @(posedge w_clk) if(w_we) r[w_wr] <= w_wdata;

  initial begin
    r[1] = 1;
    r[2] = 2;
  end
endmodule

/******************************************************************************/
module m_7segled (w_in, r_led);
  input  wire [3:0] w_in;
  output reg  [6:0] r_led;
  always @(*) begin
    case (w_in)
      4'h0  : r_led <= 7'b1111110;
      4'h1  : r_led <= 7'b0110000;
      4'h2  : r_led <= 7'b1101101;
      4'h3  : r_led <= 7'b1111001;
      4'h4  : r_led <= 7'b0110011;
      4'h5  : r_led <= 7'b1011011;
      4'h6  : r_led <= 7'b1011111;
      4'h7  : r_led <= 7'b1110000;
      4'h8  : r_led <= 7'b1111111;
      4'h9  : r_led <= 7'b1111011;
      4'ha  : r_led <= 7'b1110111;
      4'hb  : r_led <= 7'b0011111;
      4'hc  : r_led <= 7'b1001110;
      4'hd  : r_led <= 7'b0111101;
      4'he  : r_led <= 7'b1001111;
      4'hf  : r_led <= 7'b1000111;
      default:r_led <= 7'b0000000;
    endcase
  end
endmodule

`define DELAY7SEG  100000 // 200000 for 100MHz, 100000 for 50MHz
/******************************************************************************/
module m_7segcon (w_clk, w_din, r_sg, r_an);
  input  wire w_clk;
  input  wire [31:0] w_din;
  output reg [6:0] r_sg;  // cathode segments
  output reg [7:0] r_an;  // common anode

  reg [31:0] r_val   = 0;
  reg [31:0] r_cnt   = 0;
  reg  [3:0] r_in    = 0;
  reg  [2:0] r_digit = 0;
  always@(posedge w_clk) r_val <= w_din;

  always@(posedge w_clk) begin
    r_cnt <= (r_cnt>=(`DELAY7SEG-1)) ? 0 : r_cnt + 1;
    if(r_cnt==0) begin
      r_digit <= r_digit+ 1;
      if      (r_digit==0) begin r_an <= 8'b11111110; r_in <= r_val[3:0];   end
      else if (r_digit==1) begin r_an <= 8'b11111101; r_in <= r_val[7:4];   end
      else if (r_digit==2) begin r_an <= 8'b11111011; r_in <= r_val[11:8];  end
      else if (r_digit==3) begin r_an <= 8'b11110111; r_in <= r_val[15:12]; end
      else if (r_digit==4) begin r_an <= 8'b11101111; r_in <= r_val[19:16]; end
      else if (r_digit==5) begin r_an <= 8'b11011111; r_in <= r_val[23:20]; end
      else if (r_digit==6) begin r_an <= 8'b10111111; r_in <= r_val[27:24]; end
      else                 begin r_an <= 8'b01111111; r_in <= r_val[31:28]; end
    end
  end
  wire [6:0] w_segments;
  m_7segled m_7segled (r_in, w_segments);
  always@(posedge w_clk) r_sg <= ~w_segments;
endmodule
/******************************************************************************/

code140.vcd
$date
	Mon Jun  3 16:36:05 2019
$end
$version
	Icarus Verilog
$end
$timescale
	1s
$end
$scope module m_top $end
$scope module p $end
$var wire 1 ! w_clk $end
$var wire 1 " w_rst $end
$var wire 1 # w_taken $end
$var wire 32 $ w_tpc [31:0] $end
$var wire 5 % w_rt [4:0] $end
$var wire 32 & w_rslt2 [31:0] $end
$var wire 32 ' w_rslt [31:0] $end
$var wire 5 ( w_rs [4:0] $end
$var wire 32 ) w_rrt2 [31:0] $end
$var wire 32 * w_rrt [31:0] $end
$var wire 32 + w_rrs [31:0] $end
$var wire 5 , w_rd2 [4:0] $end
$var wire 5 - w_rd [4:0] $end
$var wire 32 . w_plus2_2 [31:0] $end
$var wire 32 / w_plus2_1 [31:0] $end
$var wire 32 0 w_plus1 [31:0] $end
$var wire 32 1 w_pc4 [31:0] $end
$var wire 6 2 w_op [5:0] $end
$var wire 32 3 w_imm32 [31:0] $end
$var wire 16 4 w_imm [15:0] $end
$var wire 32 5 MeWb_ldd [31:0] $end
$var wire 32 6 IfId_ir [31:0] $end
$var reg 6 7 ExMe_op [5:0] $end
$var reg 32 8 ExMe_pc [31:0] $end
$var reg 5 9 ExMe_rd2 [4:0] $end
$var reg 32 : ExMe_rrt [31:0] $end
$var reg 32 ; ExMe_rslt [31:0] $end
$var reg 1 < ExMe_w $end
$var reg 1 = ExMe_we $end
$var reg 6 > IdEx_op [5:0] $end
$var reg 32 ? IdEx_pc [31:0] $end
$var reg 5 @ IdEx_rd2 [4:0] $end
$var reg 32 A IdEx_rrs [31:0] $end
$var reg 32 B IdEx_rrt [31:0] $end
$var reg 32 C IdEx_rrt2 [31:0] $end
$var reg 6 D IdEx_rs [5:0] $end
$var reg 6 E IdEx_rt [5:0] $end
$var reg 1 F IdEx_w $end
$var reg 1 G IdEx_we $end
$var reg 32 H IfId_pc [31:0] $end
$var reg 32 I IfId_pc4 [31:0] $end
$var reg 5 J IfId_rd2 [4:0] $end
$var reg 1 K IfId_w $end
$var reg 1 L IfId_we $end
$var reg 6 M MeWb_op [5:0] $end
$var reg 32 N MeWb_pc [31:0] $end
$var reg 5 O MeWb_rd2 [4:0] $end
$var reg 32 P MeWb_rslt [31:0] $end
$var reg 1 Q MeWb_w $end
$var reg 1 R r_halt $end
$var reg 32 S r_pc [31:0] $end
$var reg 32 T r_rout [31:0] $end
$var reg 32 U r_tmp [31:0] $end
$scope module m_dmem $end
$var wire 12 V w_addr [11:0] $end
$var wire 1 ! w_clk $end
$var wire 32 W w_din [31:0] $end
$var wire 1 = w_we $end
$var reg 32 X r_dout [31:0] $end
$upscope $end
$scope module m_imem $end
$var wire 12 Y w_addr [11:0] $end
$var wire 1 ! w_clk $end
$var wire 32 Z w_din [31:0] $end
$var wire 1 [ w_we $end
$var reg 32 \ r_dout [31:0] $end
$upscope $end
$scope module m_regs $end
$var wire 1 ! w_clk $end
$var wire 5 ] w_rr1 [4:0] $end
$var wire 5 ^ w_rr2 [4:0] $end
$var wire 32 _ w_wdata [31:0] $end
$var wire 1 Q w_we $end
$var wire 5 ` w_wr [4:0] $end
$var wire 32 a w_rdata2 [31:0] $end
$var wire 32 b w_rdata1 [31:0] $end
$upscope $end
$upscope $end
$upscope $end
$enddefinitions $end
#0
$dumpvars
bx b
bx a
b0 `
b0 _
b0 ^
b0 ]
b0 \
0[
b0 Z
b0 Y
b0 X
b0 W
b0 V
b0 U
b0 T
b0 S
0R
0Q
b0 P
b0 O
b0 N
b0 M
0L
0K
b0 J
b0 I
b0 H
0G
0F
b0 E
b0 D
b0 C
b0 B
b0 A
b0 @
b0 ?
b0 >
0=
0<
b0 ;
b0 :
b0 9
b0 8
b0 7
b0 6
b0 5
b0 4
b0 3
b0 2
b100 1
b0 0
b0 /
b0 .
b0 -
b0 ,
bx +
bx *
bx )
b0 (
bx '
b0 &
b0 %
b0 $
0#
0"
0!
$end
#10
b0 '
#15
b0 )
b0 *
b0 a
b0 +
b0 b
#50
b10000000 $
b100000 3
b100000 4
b100000 6
b100000 \
b100000 5
b100000 X
1!
#53
b1 Y
b10000100 $
b100 I
b1000 1
b100 S
1F
#100
0!
#150
1!
#153
b10 Y
1<
b10001000 $
b1000 I
b100 H
b1100 1
b1000 S
#200
0!
#250
b1000 $
b10100 ,
b0 3
b0 4
b10100 %
b10100 ^
b1000 2
b100000000101000000000000000000 6
b100000000101000000000000000000 \
1!
#253
b11 Y
b1100 $
b1100 I
b1000 H
b10000 1
b1100 S
b100 ?
1Q
#265
bx *
bx a
#300
0!
#350
b1011 )
b111000 $
b10101 ,
b1011 3
b1011 4
b10101 %
b10101 ^
b100000000101010000000000001011 6
b100000000101010000000000001011 \
1!
#353
b100 Y
b100 8
bx B
b10100 @
b1000 >
b1000 ?
b111100 $
b10000 I
b1100 H
b10100 1
b10000 S
#400
0!
#450
b11000000010010000 $
b1100 ,
bx )
b110000000100000 3
b110000000100000 4
b1100 -
b0 %
b0 ^
b0 2
b110000000100000 6
b110000000100000 \
1!
#453
b1011 /
b101 Y
b1011 .
b11000000010010100 $
b10100 I
b10000 H
b11000 1
b10100 S
b1011 C
b10101 @
b1100 ?
bx :
bx W
b10100 9
b1000 7
b1000 8
b100 N
#463
b1011 '
#465
b0 )
b0 *
b0 a
#500
0!
#550
b10100 $
b1011 ,
b0 3
b0 4
b0 -
b1011 %
b1011 ^
b1000 2
b100000000010110000000000000000 6
b100000000010110000000000000000 \
1!
#553
b0 /
b10 V
b0 .
b110 Y
b10100 O
b10100 `
b1000 M
b1000 N
b1011 ;
b10101 9
b1100 8
b0 C
b0 B
b1100 @
b0 >
b10000 ?
b11000 $
b11000 I
b10100 H
b11100 1
b11000 S
#563
b0 '
#565
bx *
bx a
#600
0!
#650
b1000000000000 )
b100000000011000 $
b1000 ,
b1000000000000 3
b1000000000000 4
b10 -
b1000 %
b1000 ^
b100000000010000001000000000000 6
b100000000010000001000000000000 \
b100000000101000000000000000000 5
b100000000101000000000000000000 X
1!
#653
b111 Y
b0 V
b1011 &
b1011 _
b100000000011100 $
b11100 I
b11000 H
b100000 1
b11100 S
bx B
b1011 @
b1000 >
b10100 ?
b0 :
b0 W
b0 ;
b1100 9
b0 7
b10000 8
b10101 O
b10101 `
b1011 P
b1100 N
#700
0!
#750
b0 )
b11100 $
b1001 ,
b0 3
b0 4
b0 -
b1001 %
b1001 ^
b100000 5
b100000 X
b100000000010010000000000000000 6
b100000000010010000000000000000 \
1!
#753
b1000000000000 /
b0 &
b0 _
b1000000000000 .
b1000 Y
b1100 O
b1100 `
b0 M
b0 P
b10000 N
bx :
bx W
b1011 9
b1000 7
b10100 8
b1000000000000 C
b1000 @
b11000 ?
b100000 $
b100000 I
b11100 H
b100100 1
b100000 S
#763
b1000000000000 '
#800
0!
#850
b1010 ,
b1010 %
b1010 ^
b100000000010100000000000000000 6
b100000000010100000000000000000 \
1!
#853
b0 /
b1001 Y
b0 .
b10000000000 V
b100100 $
b100100 I
b100000 H
b101000 1
b100100 S
b0 C
b1001 @
b11100 ?
b1000000000000 ;
b1000 9
b11000 8
b1011 O
b1011 `
b1000 M
b10100 N
#863
b0 '
#900
0!
#950
b1011 ,
b1011 %
b1011 ^
b1010 (
b1010 ]
b101011 2
bx 5
bx X
b10101101010010110000000000000000 6
b10101101010010110000000000000000 \
1!
#953
b1000000000000 &
b1000000000000 _
b0 V
b1010 Y
b1000 O
b1000 `
b1000000000000 P
b11000 N
b0 ;
b1001 9
b11100 8
b1010 @
b100000 ?
b101000 $
b101000 I
b100100 H
b101100 1
b101000 S
#965
b0 *
b0 a
bx +
bx b
#1000
0!
#1050
b1 )
b101100 $
b1001 ,
b1 3
b1 4
b1001 %
b1001 ^
b1001 (
b1001 ]
b1000 2
b100001001010010000000000000001 6
b100001001010010000000000000001 \
b100000 5
b100000 X
1!
#1053
b0 0
b1011 Y
b0 &
b0 _
b110000 $
b101100 I
b101000 H
b110000 1
b101100 S
b1010 D
b0 B
bx A
1G
0F
b1011 @
b101011 >
b100100 ?
b1010 9
b100000 8
b1001 O
b1001 `
b0 P
b11100 N
#1068
b0 +
b0 b
#1100
0!
#1150
b1011 ,
b1011 %
b1011 ^
b1011 (
b1011 ]
b100001011010110000000000000001 6
b100001011010110000000000000001 \
1!
#1153
b1 /
b1 .
b1100 Y
b1010 O
b1010 `
b100000 N
b0 :
b0 W
1=
0<
b1011 9
b101011 7
b100100 8
b1001 D
b1 C
b0 A
0G
1F
b1001 @
b1000 >
b101000 ?
b110100 $
b110000 I
b101100 H
b110100 1
b110000 S
#1163
b1 '
#1200
0!
#1250
1!
#1253
b1101 Y
b111000 $
b110100 I
b110000 H
b111000 1
b110100 S
b1011 D
b1011 @
b101100 ?
b1 ;
0=
1<
b1001 9
b1000 7
b101000 8
0Q
b1011 O
b1011 `
b101011 M
b100100 N
#1300
0!
#1350
b0 5
b0 X
1!
#1353
b1 0
b1 &
b1 _
b1110 Y
1Q
b1001 O
b1001 `
b1000 M
b1 P
b101000 N
b1011 9
b101100 8
b110000 ?
b111100 $
b111000 I
b110100 H
b111100 1
b111000 S
#1363
b10 '
#1400
0!
#1450
1!
#1453
b1111 Y
b10 0
b1000000 $
b111100 I
b111000 H
b1000000 1
b111100 S
b110100 ?
b10 ;
b110000 8
b1011 O
b1011 `
b101100 N
#1463
b11 '
#1468
b1 +
b1 b
b1 *
b1 a
#1500
0!
#1550
b100 )
b1001100 $
b1010 ,
b100 3
b100 4
b1010 %
b1010 ^
b1010 (
b1010 ]
b100001010010100000000000000100 6
b100001010010100000000000000100 \
1!
#1553
b10 &
b10 _
b11 0
b10000 Y
b10 P
b110000 N
b11 ;
b110100 8
b1 B
b1 A
b111000 ?
b1010000 $
b1000000 I
b111100 H
b1000100 1
b1000000 S
#1563
b100 '
#1565
b0 *
b0 a
b0 +
b0 b
#1600
0!
#1650
b100000 $
b1001 ,
b0 )
b11111111111111111111111111111000 3
b1111111111111000 4
b11111 -
b1001 %
b1001 ^
b1000 (
b1000 ]
b101 2
b10101000010011111111111111000 6
b10101000010011111111111111000 \
1!
#1653
b100 /
b10001 Y
b100 .
b0 0
b1 V
b11 &
b11 _
b100100 $
b1000100 I
b1000000 H
b1001000 1
b1000100 S
b1010 D
b100 C
b0 B
b0 A
b1010 @
b111100 ?
b1 :
b1 W
b100 ;
b111000 8
b11 P
b110100 N
#1665
1#
b1 )
b1 *
b1 a
b1000000000000 +
b1000000000000 b
#1700
0!
#1750
0#
b11000100 $
b0 ,
b100000 3
b100000 4
b0 -
b0 %
b0 ^
b0 (
b0 ]
b0 2
b100000 5
b100000 X
b100000 6
b100000 \
1!
#1753
b1 /
b1000000000000 0
b100 &
b100 _
b1 .
b1001 Y
b100 P
b111000 N
b0 :
b0 W
b1010 9
b111100 8
b1000 D
b1 C
b1 B
b1000000000000 A
0F
b1001 @
b101 >
b1000000 ?
b11001000 $
b1001000 I
b1000100 H
b101000 1
b100100 S
#1763
b1000000000001 '
#1765
b0 )
b0 *
b0 a
b0 +
b0 b
#1800
0!
#1850
b1001000 $
b1011 ,
b0 3
b0 4
b1011 %
b1011 ^
b1010 (
b1010 ]
b101011 2
b10101101010010110000000000000000 6
b10101101010010110000000000000000 \
1!
#1853
b0 .
b0 /
b0 0
b1010 Y
b10000000000 V
b101000 $
b101000 I
b100100 H
b101100 1
b101000 S
b0 D
b0 C
b0 B
b0 A
1F
b0 @
b0 >
b1000100 ?
b1 :
b1 W
b1000000000001 ;
0<
b1001 9
b101 7
b1000000 8
b1010 O
b1010 `
b111100 N
#1863
b0 '
#1865
b100 *
b100 a
#1868
b100 +
b100 b
#1900
0!
#1950
b1 )
b101100 $
b1001 ,
b1 3
b1 4
b1001 %
b1001 ^
b1001 (
b1001 ]
b1000 2
bx 5
bx X
b100001001010010000000000000001 6
b100001001010010000000000000001 \
1!
